backo/__init__.py
backo/action.py
backo/api_toolbox.py
backo/backoffice.py
backo/collection.py
backo/current_user.py
backo/db_connector.py
backo/db_mongo_connector.py
backo/db_yml_connector.py
backo/error.py
backo/item.py
backo/log.py
backo/meta_data_handler.py
backo/patch.py
backo/reference.py
backo/request_decorators.py
backo/status.py
backo/transaction.py
backo/view.py
backo-0.0.1.dist-info/METADATA
backo-0.0.1.dist-info/WHEEL
backo-0.0.1.dist-info/licenses/LICENSE
backo-0.0.1.dist-info/RECORD
