Metadata-Version: 2.4
Name: backo
Version: 0.0.1
Summary: Back office low code
Project-URL: GitHub, https://github.com/bwallrich/backo
Project-URL: Homepage, https://github.com/bwallrich/backo
Project-URL: Issues, https://github.com/bwallrich/backo/issues
Author-email: Bertrand Wallrich <Bertrand.Wallrich@inria.fr>
License: MIT License
License-File: LICENSE
Classifier: License :: OSI Approved :: MIT License
Classifier: Operating System :: OS Independent
Classifier: Programming Language :: Python :: 3
Requires-Python: >=3.8
